docker/__init__.py
docker/client.py
docker/constants.py
docker/errors.py
docker/tls.py
docker/version.py
docker/api/__init__.py
docker/api/build.py
docker/api/container.py
docker/api/daemon.py
docker/api/exec_api.py
docker/api/image.py
docker/api/network.py
docker/api/service.py
docker/api/swarm.py
docker/api/volume.py
docker/auth/__init__.py
docker/auth/auth.py
docker/ssladapter/__init__.py
docker/ssladapter/ssladapter.py
docker/transport/__init__.py
docker/transport/npipeconn.py
docker/transport/npipesocket.py
docker/transport/unixconn.py
docker/types/__init__.py
docker/types/base.py
docker/types/containers.py
docker/types/services.py
docker/types/swarm.py
docker/utils/__init__.py
docker/utils/decorators.py
docker/utils/socket.py
docker/utils/types.py
docker/utils/utils.py
docker/utils/ports/__init__.py
docker/utils/ports/ports.py
docker_py-1.10.5.dist-info/DESCRIPTION.rst
docker_py-1.10.5.dist-info/METADATA
docker_py-1.10.5.dist-info/RECORD
docker_py-1.10.5.dist-info/WHEEL
docker_py-1.10.5.dist-info/metadata.json
docker_py-1.10.5.dist-info/top_level.txt
