Metadata-Version: 2.0
Name: docker-py
Version: 1.10.5
Summary: Python client for Docker.
Home-page: https://github.com/docker/docker-py/
Author: Joffrey F
Author-email: joffrey@docker.com
License: UNKNOWN
Platform: UNKNOWN
Classifier: Development Status :: 4 - Beta
Classifier: Environment :: Other Environment
Classifier: Intended Audience :: Developers
Classifier: Operating System :: OS Independent
Classifier: Programming Language :: Python
Classifier: Programming Language :: Python :: 2
Classifier: Programming Language :: Python :: 2.6
Classifier: Programming Language :: Python :: 2.7
Classifier: Programming Language :: Python :: 3
Classifier: Programming Language :: Python :: 3.3
Classifier: Programming Language :: Python :: 3.4
Classifier: Programming Language :: Python :: 3.5
Classifier: Topic :: Utilities
Classifier: License :: OSI Approved :: Apache Software License
Requires-Dist: docker-pycreds (>=0.2.1)
Requires-Dist: requests (>=2.5.2,!=2.11.0)
Requires-Dist: six (>=1.4.0)
Requires-Dist: websocket-client (>=0.32.0)
Requires-Dist: ipaddress (>=1.0.16); python_version < "3.3"
Requires-Dist: backports.ssl-match-hostname (>=3.5); python_version < "3.5"
